rocket2/__init__.py
rocket2/rocket2.py
rocket2/rocket22.py
rocket_nabahat_imane-1.0.1.dist-info/licenses/LICENSE.txt
rocket_nabahat_imane-1.0.1.dist-info/METADATA
rocket_nabahat_imane-1.0.1.dist-info/WHEEL
rocket_nabahat_imane-1.0.1.dist-info/top_level.txt
rocket_nabahat_imane-1.0.1.dist-info/RECORD
