Metadata-Version: 2.4
Name: rocket_nabahat_imane
Version: 1.0.1
Summary: An awesome package that does something
Home-page: http://pypi.python.org/pypi/rocket/
Author: MERZOUK nabahat imane
Author-email: ni.merzouk@esi-sba.dz
License: LICENSE.txt
License-File: LICENSE.txt
Dynamic: author
Dynamic: author-email
Dynamic: description
Dynamic: description-content-type
Dynamic: home-page
Dynamic: license
Dynamic: license-file
Dynamic: summary
